{
  "node0": {
    "pid": 3137006,
    "port": 40000
  },
  "node1": {
    "pid": 3137008,
    "port": 40001
  },
  "node2": {
    "pid": 3137009,
    "port": 40002
  },
  "node3": {
    "pid": 3137011,
    "port": 40003
  },
  "node4": {
    "pid": 3137013,
    "port": 40004
  },
  "node5": {
    "pid": 3137015,
    "port": 40005
  },
  "node6": {
    "pid": 3137016,
    "port": 40006
  },
  "node7": {
    "pid": 3137018,
    "port": 40007
  },
  "node8": {
    "pid": 3137020,
    "port": 40008
  },
  "node9": {
    "pid": 3137022,
    "port": 40009
  },
  "node10": {
    "pid": 3137023,
    "port": 40010
  },
  "node11": {
    "pid": 3137025,
    "port": 40011
  },
  "node12": {
    "pid": 3137027,
    "port": 40012
  },
  "node13": {
    "pid": 3137029,
    "port": 40013
  },
  "node14": {
    "pid": 3137030,
    "port": 40014
  },
  "node15": {
    "pid": 3137032,
    "port": 40015
  },
  "node16": {
    "pid": 3137034,
    "port": 40016
  },
  "node17": {
    "pid": 3137036,
    "port": 40017
  },
  "node18": {
    "pid": 3137037,
    "port": 40018
  },
  "node19": {
    "pid": 3137039,
    "port": 40019
  }
}